bis_fetcher/__cli__.py
bis_fetcher/__init__.py
bis_fetcher/_version.py
bis_fetcher/conf/__init__.py
bis_fetcher/conf/about/bis_fetcher.yaml
bis_fetcher/fetcher/__init__.py
bis_fetcher/fetcher/base.py
bis_fetcher/fetcher/bis.py
bis_fetcher/fetcher/chromedriver.py
bis_fetcher/py.typed
bis_fetcher-0.6.0.dist-info/LICENSE
bis_fetcher-0.6.0.dist-info/METADATA
bis_fetcher-0.6.0.dist-info/WHEEL
bis_fetcher-0.6.0.dist-info/entry_points.txt
bis_fetcher-0.6.0.dist-info/RECORD
