Metadata-Version: 2.1
Name: bis-fetcher
Version: 0.6.0
Summary: A python library to scrape the BIS website
Home-page: https://entelecheia.github.io/bis-fetcher
License: MIT
Author: Young Joon Lee
Author-email: entelecheia@hotmail.com
Requires-Python: >=3.8.1,<3.12
Classifier: License :: OSI Approved :: MIT License
Classifier: Programming Language :: Python :: 3
Classifier: Programming Language :: Python :: 3.9
Classifier: Programming Language :: Python :: 3.10
Classifier: Programming Language :: Python :: 3.11
Requires-Dist: click (>=8.1.3,<9.0.0)
Requires-Dist: hyfi (>=1.34.0,<2.0.0)
Requires-Dist: selenium (>=4.15.2,<5.0.0)
Project-URL: Repository, https://github.com/entelecheia/bis-fetcher
